br_gender/__init__.py
br_gender/base.py
br_gender/gender_by_name.json
br_gender-0.1.0.dist-info/LICENSE
br_gender-0.1.0.dist-info/METADATA
br_gender-0.1.0.dist-info/WHEEL
br_gender-0.1.0.dist-info/top_level.txt
br_gender-0.1.0.dist-info/RECORD
